[
    {
    "isim": "Beykoz",
    "createdOn": "28-01-2022",
    "resimUrl": "https://raw.githubusercontent.com/behluloral/finalproje/main/beykoz.png"
    },
    {
        "isim": "Beylikdüzü",
        "createdOn": "28-01-2022",
        "resimUrl": "https://raw.githubusercontent.com/behluloral/finalproje/main/beylikduzu.png"
    },
    {
        "isim": "Üsküdar",
        "createdOn": "28-01-2022",
        "resimUrl": "https://raw.githubusercontent.com/behluloral/finalproje/main/uskudar.png"
    },
    {
        "isim": "Kadıköy",
        "createdOn": "28-01-2022",
        "resimUrl": "https://raw.githubusercontent.com/behluloral/finalproje/main/kadikoy.png"
    },
    {
        "isim": "Taksim",
        "createdOn": "28-01-2022",
        "resimUrl": "https://raw.githubusercontent.com/behluloral/finalproje/main/taksimm.png"
    },
    {
        "isim": "Beşiktaş",
        "createdOn": "28-01-2022",
        "resimUrl": "https://raw.githubusercontent.com/behluloral/finalproje/main/besiktas.png"
    }
 
]
